tencentcloud/__init__.py
tencentcloud/ams/__init__.py
tencentcloud/ams/v20200608/__init__.py
tencentcloud/ams/v20200608/ams_client.py
tencentcloud/ams/v20200608/ams_client_async.py
tencentcloud/ams/v20200608/errorcodes.py
tencentcloud/ams/v20200608/models.py
tencentcloud/ams/v20201229/__init__.py
tencentcloud/ams/v20201229/ams_client.py
tencentcloud/ams/v20201229/ams_client_async.py
tencentcloud/ams/v20201229/errorcodes.py
tencentcloud/ams/v20201229/models.py
tencentcloud_sdk_python_ams-3.1.19.dist-info/METADATA
tencentcloud_sdk_python_ams-3.1.19.dist-info/WHEEL
tencentcloud_sdk_python_ams-3.1.19.dist-info/top_level.txt
tencentcloud_sdk_python_ams-3.1.19.dist-info/RECORD
